automate/__init__.py
automate/_vendor/__init__.py
automate/_vendor/patchwork/__init__.py
automate/_vendor/patchwork/_version.py
automate/_vendor/patchwork/environment.py
automate/_vendor/patchwork/files.py
automate/_vendor/patchwork/info.py
automate/_vendor/patchwork/packages/__init__.py
automate/_vendor/patchwork/transfers.py
automate/_vendor/patchwork/util.py
automate/_vendor/patchwork-1.0.1.dist-info/DESCRIPTION.rst
automate/_vendor/patchwork-1.0.1.dist-info/INSTALLER
automate/_vendor/patchwork-1.0.1.dist-info/LICENSE.txt
automate/_vendor/patchwork-1.0.1.dist-info/METADATA
automate/_vendor/patchwork-1.0.1.dist-info/RECORD
automate/_vendor/patchwork-1.0.1.dist-info/REQUESTED
automate/_vendor/patchwork-1.0.1.dist-info/WHEEL
automate/_vendor/patchwork-1.0.1.dist-info/metadata.json
automate/_vendor/patchwork-1.0.1.dist-info/top_level.txt
automate/_version.py
automate/board.py
automate/builder/__init__.py
automate/builder/builder.py
automate/builder/cmake.py
automate/builder/kernel.py
automate/builder/make.py
automate/compiler.py
automate/config.py
automate/context.py
automate/database/__init__.py
automate/database/database.py
automate/database/queries/delete_lock_for_board.sql
automate/database/queries/init_database.sql
automate/database/queries/insert_board.sql
automate/database/queries/insert_lock.sql
automate/database/queries/select_all_boards.sql
automate/database/queries/select_all_cpu_cores_for_board.sql
automate/database/queries/select_all_docs_for_board.sql
automate/database/queries/select_all_kernels_for_os.sql
automate/database/queries/select_lock_for_board.sql
automate/database/queries/select_os_for_board.sql
automate/database/queries/transfer_lock_for_board.sql
automate/database/queries/update_lock_lease_for_board.sql
automate/executor.py
automate/loader.py
automate/locks.py
automate/main.py
automate/model/__init__.py
automate/model/board.py
automate/model/common.py
automate/model/compiler.py
automate/model/metadata.py
automate/model/model_base.py
automate/model/user.py
automate/tasks/__init__.py
automate/tasks/admin.py
automate/tasks/board.py
automate/tasks/cmake.py
automate/tasks/common.py
automate/tasks/compiler.py
automate/tasks/database.py
automate/tasks/kernel.py
automate/tasks/make.py
automate/utils/__init__.py
automate/utils/appdirs.py
automate/utils/cpuinfo.py
automate/utils/cpuinfo_arm.py
automate/utils/kernel.py
automate/utils/network.py
automate/utils/uboot.py
board_automate-0.4.1.dist-info/LICENSE
board_automate-0.4.1.dist-info/METADATA
board_automate-0.4.1.dist-info/WHEEL
board_automate-0.4.1.dist-info/entry_points.txt
board_automate-0.4.1.dist-info/RECORD
